kusa/__init__.py
kusa/client.py
kusa/config.py
kusa/encryption_manager.py
kusa/exceptions.py
kusa/kusaSdk.py
kusa/model_manager.py
kusa/preprocessing_manager.py
kusa/utils.py
kusa-0.1.0.dist-info/licenses/LICENSE.txt
kusa-0.1.0.dist-info/METADATA
kusa-0.1.0.dist-info/WHEEL
kusa-0.1.0.dist-info/top_level.txt
kusa-0.1.0.dist-info/RECORD
