Metadata-Version: 2.4
Name: kusa
Version: 0.1.0
Summary: Kusa SDK: Securely access, preprocess, and train machine learning models on datasets with enhanced privacy features.
Home-page: https://github.com/Nesril/kusaSdk
Author: Nesredin  / HAWD Techs
Author-email: nesredinhaji715@gmail.com
License: MIT
Project-URL: Documentation, http://kuusa.netlify.app/docs
Project-URL: Source, https://github.com/Nesril/kusaSdk
Project-URL: Tracker, https://github.com/Nesril/kusaSdk/issues
Keywords: kusa sdk dataset machine-learning ai secure privacy data preprocessing nlp tabular
Classifier: License :: OSI Approved :: MIT License
Classifier: Development Status :: 3 - Alpha
Classifier: Intended Audience :: Developers
Classifier: Intended Audience :: Science/Research
Classifier: Topic :: Software Development :: Libraries :: Python Modules
Classifier: Topic :: Scientific/Engineering :: Artificial Intelligence
Classifier: Topic :: Security :: Cryptography
Classifier: Programming Language :: Python
Classifier: Programming Language :: Python :: 3
Classifier: Programming Language :: Python :: 3.7
Classifier: Programming Language :: Python :: 3.8
Classifier: Programming Language :: Python :: 3.9
Classifier: Programming Language :: Python :: 3.10
Classifier: Programming Language :: Python :: 3.11
Classifier: Programming Language :: Python :: 3.12
Classifier: Programming Language :: Python :: Implementation :: CPython
Classifier: Operating System :: OS Independent
Requires-Python: >=3.7.0
License-File: LICENSE.txt
Requires-Dist: requests>=2.20.0
Requires-Dist: pandas>=1.1.0
Requires-Dist: cryptography>=3.0
Requires-Dist: numpy>=1.18.0
Requires-Dist: nltk>=3.5
Requires-Dist: joblib>=0.14.0
Requires-Dist: scikit-learn>=0.23.0
Requires-Dist: python-dotenv>=0.10.0
Provides-Extra: tensorflow
Requires-Dist: tensorflow>=2.2.0; extra == "tensorflow"
Provides-Extra: pytorch
Requires-Dist: torch>=1.8.0; extra == "pytorch"
Provides-Extra: all-ml
Requires-Dist: tensorflow>=2.2.0; extra == "all-ml"
Requires-Dist: torch>=1.8.0; extra == "all-ml"
Dynamic: author
Dynamic: author-email
Dynamic: classifier
Dynamic: description
Dynamic: description-content-type
Dynamic: home-page
Dynamic: keywords
Dynamic: license
Dynamic: license-file
Dynamic: project-url
Dynamic: provides-extra
Dynamic: requires-dist
Dynamic: requires-python
Dynamic: summary
